{
  "__inputs": [],
  "__requires": [],
  "annotations": {
    "list": [
      {
        "builtIn": 1,
        "datasource": {
          "type": "grafana",
          "uid": "-- Grafana --"
        },
        "enable": true,
        "hide": true,
        "iconColor": "rgba(0, 211, 255, 1)",
        "name": "Annotations & Alerts",
        "type": "dashboard"
      }
    ]
  },
  "description": "🌡 Climate & HVAC",
  "editable": true,
  "fiscalYearStartMonth": 0,
  "graphTooltip": 1,
  "id": null,
  "links": [],
  "panels": [
    {
      "type": "row",
      "title": "🌡 Current Temperatures",
      "id": 1,
      "collapsed": false,
      "gridPos": {
        "h": 1,
        "w": 24,
        "x": 0,
        "y": 0
      },
      "panels": []
    },
    {
      "type": "stat",
      "title": "🌤 Outdoor",
      "id": 2,
      "gridPos": {
        "h": 4,
        "w": 4,
        "x": 0,
        "y": 1
      },
      "datasource": {
        "type": "influxdb",
        "uid": "cfecbpgdhs5j4b"
      },
      "options": {
        "colorMode": "background",
        "graphMode": "none",
        "justifyMode": "center",
        "orientation": "auto",
        "reduceOptions": {
          "calcs": [
            "lastNotNull"
          ],
          "fields": "",
          "values": false
        },
        "textMode": "auto"
      },
      "fieldConfig": {
        "defaults": {
          "unit": "°F",
          "thresholds": {
            "mode": "absolute",
            "steps": [
              {
                "color": "blue",
                "value": null
              },
              {
                "color": "green",
                "value": 65
              },
              {
                "color": "yellow",
                "value": 78
              },
              {
                "color": "red",
                "value": 85
              }
            ]
          },
          "mappings": [],
          "color": {
            "mode": "thresholds"
          }
        },
        "overrides": []
      },
      "targets": [
        {
          "datasource": {
            "type": "influxdb",
            "uid": "cfecbpgdhs5j4b"
          },
          "query": "from(bucket: \"bartos-homeassistant\")\n  |> range(start: -5m)\n  |> filter(fn: (r) => r._measurement == \"°F\" and r._field == \"value\" and r.entity_id == \"lansing_st_weather_temp\")\n  |> last()",
          "refId": "A"
        }
      ]
    },
    {
      "type": "stat",
      "title": "🏠 Living Room",
      "id": 3,
      "gridPos": {
        "h": 4,
        "w": 4,
        "x": 4,
        "y": 1
      },
      "datasource": {
        "type": "influxdb",
        "uid": "cfecbpgdhs5j4b"
      },
      "options": {
        "colorMode": "background",
        "graphMode": "none",
        "justifyMode": "center",
        "orientation": "auto",
        "reduceOptions": {
          "calcs": [
            "lastNotNull"
          ],
          "fields": "",
          "values": false
        },
        "textMode": "auto"
      },
      "fieldConfig": {
        "defaults": {
          "unit": "°F",
          "thresholds": {
            "mode": "absolute",
            "steps": [
              {
                "color": "blue",
                "value": null
              },
              {
                "color": "green",
                "value": 65
              },
              {
                "color": "yellow",
                "value": 78
              },
              {
                "color": "red",
                "value": 85
              }
            ]
          },
          "mappings": [],
          "color": {
            "mode": "thresholds"
          }
        },
        "overrides": []
      },
      "targets": [
        {
          "datasource": {
            "type": "influxdb",
            "uid": "cfecbpgdhs5j4b"
          },
          "query": "from(bucket: \"bartos-homeassistant\")\n  |> range(start: -5m)\n  |> filter(fn: (r) => r._measurement == \"°F\" and r._field == \"value\" and r.entity_id == \"living_room_temperature\")\n  |> last()",
          "refId": "A"
        }
      ]
    },
    {
      "type": "stat",
      "title": "🛏 Bedroom",
      "id": 4,
      "gridPos": {
        "h": 4,
        "w": 4,
        "x": 8,
        "y": 1
      },
      "datasource": {
        "type": "influxdb",
        "uid": "cfecbpgdhs5j4b"
      },
      "options": {
        "colorMode": "background",
        "graphMode": "none",
        "justifyMode": "center",
        "orientation": "auto",
        "reduceOptions": {
          "calcs": [
            "lastNotNull"
          ],
          "fields": "",
          "values": false
        },
        "textMode": "auto"
      },
      "fieldConfig": {
        "defaults": {
          "unit": "°F",
          "thresholds": {
            "mode": "absolute",
            "steps": [
              {
                "color": "blue",
                "value": null
              },
              {
                "color": "green",
                "value": 65
              },
              {
                "color": "yellow",
                "value": 78
              },
              {
                "color": "red",
                "value": 85
              }
            ]
          },
          "mappings": [],
          "color": {
            "mode": "thresholds"
          }
        },
        "overrides": []
      },
      "targets": [
        {
          "datasource": {
            "type": "influxdb",
            "uid": "cfecbpgdhs5j4b"
          },
          "query": "from(bucket: \"bartos-homeassistant\")\n  |> range(start: -5m)\n  |> filter(fn: (r) => r._measurement == \"°F\" and r._field == \"value\" and r.entity_id == \"bedroom_temperature\")\n  |> last()",
          "refId": "A"
        }
      ]
    },
    {
      "type": "stat",
      "title": "🏢 Office",
      "id": 5,
      "gridPos": {
        "h": 4,
        "w": 4,
        "x": 12,
        "y": 1
      },
      "datasource": {
        "type": "influxdb",
        "uid": "cfecbpgdhs5j4b"
      },
      "options": {
        "colorMode": "background",
        "graphMode": "none",
        "justifyMode": "center",
        "orientation": "auto",
        "reduceOptions": {
          "calcs": [
            "lastNotNull"
          ],
          "fields": "",
          "values": false
        },
        "textMode": "auto"
      },
      "fieldConfig": {
        "defaults": {
          "unit": "°F",
          "thresholds": {
            "mode": "absolute",
            "steps": [
              {
                "color": "blue",
                "value": null
              },
              {
                "color": "green",
                "value": 65
              },
              {
                "color": "yellow",
                "value": 78
              },
              {
                "color": "red",
                "value": 85
              }
            ]
          },
          "mappings": [],
          "color": {
            "mode": "thresholds"
          }
        },
        "overrides": []
      },
      "targets": [
        {
          "datasource": {
            "type": "influxdb",
            "uid": "cfecbpgdhs5j4b"
          },
          "query": "from(bucket: \"bartos-homeassistant\")\n  |> range(start: -5m)\n  |> filter(fn: (r) => r._measurement == \"°F\" and r._field == \"value\" and r.entity_id == \"office_temperature\")\n  |> last()",
          "refId": "A"
        }
      ]
    },
    {
      "type": "stat",
      "title": "🍳 Kitchen",
      "id": 6,
      "gridPos": {
        "h": 4,
        "w": 4,
        "x": 16,
        "y": 1
      },
      "datasource": {
        "type": "influxdb",
        "uid": "cfecbpgdhs5j4b"
      },
      "options": {
        "colorMode": "background",
        "graphMode": "none",
        "justifyMode": "center",
        "orientation": "auto",
        "reduceOptions": {
          "calcs": [
            "lastNotNull"
          ],
          "fields": "",
          "values": false
        },
        "textMode": "auto"
      },
      "fieldConfig": {
        "defaults": {
          "unit": "°F",
          "thresholds": {
            "mode": "absolute",
            "steps": [
              {
                "color": "blue",
                "value": null
              },
              {
                "color": "green",
                "value": 65
              },
              {
                "color": "yellow",
                "value": 78
              },
              {
                "color": "red",
                "value": 85
              }
            ]
          },
          "mappings": [],
          "color": {
            "mode": "thresholds"
          }
        },
        "overrides": []
      },
      "targets": [
        {
          "datasource": {
            "type": "influxdb",
            "uid": "cfecbpgdhs5j4b"
          },
          "query": "from(bucket: \"bartos-homeassistant\")\n  |> range(start: -5m)\n  |> filter(fn: (r) => r._measurement == \"°F\" and r._field == \"value\" and r.entity_id == \"kitchen_zigbee_temperature_temperature\")\n  |> last()",
          "refId": "A"
        }
      ]
    },
    {
      "type": "stat",
      "title": "🚿 Bathroom",
      "id": 7,
      "gridPos": {
        "h": 4,
        "w": 4,
        "x": 20,
        "y": 1
      },
      "datasource": {
        "type": "influxdb",
        "uid": "cfecbpgdhs5j4b"
      },
      "options": {
        "colorMode": "background",
        "graphMode": "none",
        "justifyMode": "center",
        "orientation": "auto",
        "reduceOptions": {
          "calcs": [
            "lastNotNull"
          ],
          "fields": "",
          "values": false
        },
        "textMode": "auto"
      },
      "fieldConfig": {
        "defaults": {
          "unit": "°F",
          "thresholds": {
            "mode": "absolute",
            "steps": [
              {
                "color": "blue",
                "value": null
              },
              {
                "color": "green",
                "value": 65
              },
              {
                "color": "yellow",
                "value": 78
              },
              {
                "color": "red",
                "value": 85
              }
            ]
          },
          "mappings": [],
          "color": {
            "mode": "thresholds"
          }
        },
        "overrides": []
      },
      "targets": [
        {
          "datasource": {
            "type": "influxdb",
            "uid": "cfecbpgdhs5j4b"
          },
          "query": "from(bucket: \"bartos-homeassistant\")\n  |> range(start: -5m)\n  |> filter(fn: (r) => r._measurement == \"°F\" and r._field == \"value\" and r.entity_id == \"bathroom_temperature\")\n  |> last()",
          "refId": "A"
        }
      ]
    },
    {
      "type": "stat",
      "title": "🏚 Basement",
      "id": 8,
      "gridPos": {
        "h": 4,
        "w": 4,
        "x": 0,
        "y": 5
      },
      "datasource": {
        "type": "influxdb",
        "uid": "cfecbpgdhs5j4b"
      },
      "options": {
        "colorMode": "background",
        "graphMode": "none",
        "justifyMode": "center",
        "orientation": "auto",
        "reduceOptions": {
          "calcs": [
            "lastNotNull"
          ],
          "fields": "",
          "values": false
        },
        "textMode": "auto"
      },
      "fieldConfig": {
        "defaults": {
          "unit": "°F",
          "thresholds": {
            "mode": "absolute",
            "steps": [
              {
                "color": "blue",
                "value": null
              },
              {
                "color": "green",
                "value": 65
              },
              {
                "color": "yellow",
                "value": 78
              },
              {
                "color": "red",
                "value": 85
              }
            ]
          },
          "mappings": [],
          "color": {
            "mode": "thresholds"
          }
        },
        "overrides": []
      },
      "targets": [
        {
          "datasource": {
            "type": "influxdb",
            "uid": "cfecbpgdhs5j4b"
          },
          "query": "from(bucket: \"bartos-homeassistant\")\n  |> range(start: -5m)\n  |> filter(fn: (r) => r._measurement == \"°F\" and r._field == \"value\" and r.entity_id == \"basement_temperature\")\n  |> last()",
          "refId": "A"
        }
      ]
    },
    {
      "type": "stat",
      "title": "🧊 Fridge",
      "id": 9,
      "gridPos": {
        "h": 4,
        "w": 4,
        "x": 4,
        "y": 5
      },
      "datasource": {
        "type": "influxdb",
        "uid": "cfecbpgdhs5j4b"
      },
      "options": {
        "colorMode": "background",
        "graphMode": "none",
        "justifyMode": "center",
        "orientation": "auto",
        "reduceOptions": {
          "calcs": [
            "lastNotNull"
          ],
          "fields": "",
          "values": false
        },
        "textMode": "auto"
      },
      "fieldConfig": {
        "defaults": {
          "unit": "°F",
          "thresholds": {
            "mode": "absolute",
            "steps": [
              {
                "color": "blue",
                "value": null
              },
              {
                "color": "green",
                "value": 65
              },
              {
                "color": "yellow",
                "value": 78
              },
              {
                "color": "red",
                "value": 85
              }
            ]
          },
          "mappings": [],
          "color": {
            "mode": "thresholds"
          }
        },
        "overrides": []
      },
      "targets": [
        {
          "datasource": {
            "type": "influxdb",
            "uid": "cfecbpgdhs5j4b"
          },
          "query": "from(bucket: \"bartos-homeassistant\")\n  |> range(start: -5m)\n  |> filter(fn: (r) => r._measurement == \"°F\" and r._field == \"value\" and r.entity_id == \"chill_box_fridge_temperature\")\n  |> last()",
          "refId": "A"
        }
      ]
    },
    {
      "type": "stat",
      "title": "❄ Freezer",
      "id": 10,
      "gridPos": {
        "h": 4,
        "w": 4,
        "x": 8,
        "y": 5
      },
      "datasource": {
        "type": "influxdb",
        "uid": "cfecbpgdhs5j4b"
      },
      "options": {
        "colorMode": "background",
        "graphMode": "none",
        "justifyMode": "center",
        "orientation": "auto",
        "reduceOptions": {
          "calcs": [
            "lastNotNull"
          ],
          "fields": "",
          "values": false
        },
        "textMode": "auto"
      },
      "fieldConfig": {
        "defaults": {
          "unit": "°F",
          "thresholds": {
            "mode": "absolute",
            "steps": [
              {
                "color": "blue",
                "value": null
              },
              {
                "color": "green",
                "value": 65
              },
              {
                "color": "yellow",
                "value": 78
              },
              {
                "color": "red",
                "value": 85
              }
            ]
          },
          "mappings": [],
          "color": {
            "mode": "thresholds"
          }
        },
        "overrides": []
      },
      "targets": [
        {
          "datasource": {
            "type": "influxdb",
            "uid": "cfecbpgdhs5j4b"
          },
          "query": "from(bucket: \"bartos-homeassistant\")\n  |> range(start: -5m)\n  |> filter(fn: (r) => r._measurement == \"°F\" and r._field == \"value\" and r.entity_id == \"chill_box_freezer_temperature\")\n  |> last()",
          "refId": "A"
        }
      ]
    },
    {
      "type": "row",
      "title": "📈 Temperature History",
      "id": 11,
      "collapsed": false,
      "gridPos": {
        "h": 1,
        "w": 24,
        "x": 0,
        "y": 9
      },
      "panels": []
    },
    {
      "type": "timeseries",
      "title": "🌡 Per-Room Temperatures",
      "id": 12,
      "gridPos": {
        "h": 10,
        "w": 24,
        "x": 0,
        "y": 10
      },
      "datasource": {
        "type": "influxdb",
        "uid": "cfecbpgdhs5j4b"
      },
      "options": {
        "legend": {
          "displayMode": "list",
          "placement": "bottom",
          "showLegend": true
        },
        "tooltip": {
          "mode": "multi",
          "sort": "none"
        }
      },
      "fieldConfig": {
        "defaults": {
          "unit": "°F",
          "color": {
            "mode": "palette-classic"
          }
        },
        "overrides": []
      },
      "targets": [
        {
          "datasource": {
            "type": "influxdb",
            "uid": "cfecbpgdhs5j4b"
          },
          "query": "from(bucket: \"bartos-homeassistant\")\n  |> range(start: v.timeRangeStart, stop: v.timeRangeStop)\n  |> filter(fn: (r) => r._measurement == \"°F\" and r._field == \"value\" and (r.entity_id == \"bedroom_temperature\" or r.entity_id == \"living_room_temperature\" or r.entity_id == \"office_temperature\" or r.entity_id == \"basement_temperature\" or r.entity_id == \"kitchen_zigbee_temperature_temperature\" or r.entity_id == \"bathroom_temperature\" or r.entity_id == \"lansing_st_weather_temp\"))\n  |> map(fn: (r) => ({r with _field: r.entity_id}))",
          "refId": "A"
        }
      ]
    },
    {
      "type": "row",
      "title": "💧 Humidity",
      "id": 13,
      "collapsed": false,
      "gridPos": {
        "h": 1,
        "w": 24,
        "x": 0,
        "y": 20
      },
      "panels": []
    },
    {
      "type": "stat",
      "title": "🏠 House Avg",
      "id": 14,
      "gridPos": {
        "h": 4,
        "w": 4,
        "x": 0,
        "y": 21
      },
      "datasource": {
        "type": "influxdb",
        "uid": "cfecbpgdhs5j4b"
      },
      "options": {
        "colorMode": "background",
        "graphMode": "none",
        "justifyMode": "center",
        "orientation": "auto",
        "reduceOptions": {
          "calcs": [
            "lastNotNull"
          ],
          "fields": "",
          "values": false
        },
        "textMode": "auto"
      },
      "fieldConfig": {
        "defaults": {
          "unit": "%",
          "thresholds": {
            "mode": "absolute",
            "steps": [
              {
                "color": "green",
                "value": null
              }
            ]
          },
          "mappings": [],
          "color": {
            "mode": "thresholds"
          }
        },
        "overrides": []
      },
      "targets": [
        {
          "datasource": {
            "type": "influxdb",
            "uid": "cfecbpgdhs5j4b"
          },
          "query": "from(bucket: \"bartos-homeassistant\")\n  |> range(start: -5m)\n  |> filter(fn: (r) => r._measurement == \"%\" and r._field == \"value\" and r.entity_id == \"average_house_humidity\")\n  |> last()",
          "refId": "A"
        }
      ]
    },
    {
      "type": "stat",
      "title": "🚿 Bathroom",
      "id": 15,
      "gridPos": {
        "h": 4,
        "w": 4,
        "x": 4,
        "y": 21
      },
      "datasource": {
        "type": "influxdb",
        "uid": "cfecbpgdhs5j4b"
      },
      "options": {
        "colorMode": "background",
        "graphMode": "none",
        "justifyMode": "center",
        "orientation": "auto",
        "reduceOptions": {
          "calcs": [
            "lastNotNull"
          ],
          "fields": "",
          "values": false
        },
        "textMode": "auto"
      },
      "fieldConfig": {
        "defaults": {
          "unit": "%",
          "thresholds": {
            "mode": "absolute",
            "steps": [
              {
                "color": "green",
                "value": null
              }
            ]
          },
          "mappings": [],
          "color": {
            "mode": "thresholds"
          }
        },
        "overrides": []
      },
      "targets": [
        {
          "datasource": {
            "type": "influxdb",
            "uid": "cfecbpgdhs5j4b"
          },
          "query": "from(bucket: \"bartos-homeassistant\")\n  |> range(start: -5m)\n  |> filter(fn: (r) => r._measurement == \"%\" and r._field == \"value\" and r.entity_id == \"bathroom_zigbee_temperature_humidity\")\n  |> last()",
          "refId": "A"
        }
      ]
    },
    {
      "type": "stat",
      "title": "🛏 Bedroom",
      "id": 16,
      "gridPos": {
        "h": 4,
        "w": 4,
        "x": 8,
        "y": 21
      },
      "datasource": {
        "type": "influxdb",
        "uid": "cfecbpgdhs5j4b"
      },
      "options": {
        "colorMode": "background",
        "graphMode": "none",
        "justifyMode": "center",
        "orientation": "auto",
        "reduceOptions": {
          "calcs": [
            "lastNotNull"
          ],
          "fields": "",
          "values": false
        },
        "textMode": "auto"
      },
      "fieldConfig": {
        "defaults": {
          "unit": "%",
          "thresholds": {
            "mode": "absolute",
            "steps": [
              {
                "color": "green",
                "value": null
              }
            ]
          },
          "mappings": [],
          "color": {
            "mode": "thresholds"
          }
        },
        "overrides": []
      },
      "targets": [
        {
          "datasource": {
            "type": "influxdb",
            "uid": "cfecbpgdhs5j4b"
          },
          "query": "from(bucket: \"bartos-homeassistant\")\n  |> range(start: -5m)\n  |> filter(fn: (r) => r._measurement == \"%\" and r._field == \"value\" and r.entity_id == \"bedroom_zigbee_tempurature_humidity\")\n  |> last()",
          "refId": "A"
        }
      ]
    },
    {
      "type": "stat",
      "title": "🍳 Kitchen",
      "id": 17,
      "gridPos": {
        "h": 4,
        "w": 4,
        "x": 12,
        "y": 21
      },
      "datasource": {
        "type": "influxdb",
        "uid": "cfecbpgdhs5j4b"
      },
      "options": {
        "colorMode": "background",
        "graphMode": "none",
        "justifyMode": "center",
        "orientation": "auto",
        "reduceOptions": {
          "calcs": [
            "lastNotNull"
          ],
          "fields": "",
          "values": false
        },
        "textMode": "auto"
      },
      "fieldConfig": {
        "defaults": {
          "unit": "%",
          "thresholds": {
            "mode": "absolute",
            "steps": [
              {
                "color": "green",
                "value": null
              }
            ]
          },
          "mappings": [],
          "color": {
            "mode": "thresholds"
          }
        },
        "overrides": []
      },
      "targets": [
        {
          "datasource": {
            "type": "influxdb",
            "uid": "cfecbpgdhs5j4b"
          },
          "query": "from(bucket: \"bartos-homeassistant\")\n  |> range(start: -5m)\n  |> filter(fn: (r) => r._measurement == \"%\" and r._field == \"value\" and r.entity_id == \"kitchen_zigbee_temperature_humidity\")\n  |> last()",
          "refId": "A"
        }
      ]
    },
    {
      "type": "stat",
      "title": "🌤 Outdoor",
      "id": 18,
      "gridPos": {
        "h": 4,
        "w": 4,
        "x": 16,
        "y": 21
      },
      "datasource": {
        "type": "influxdb",
        "uid": "cfecbpgdhs5j4b"
      },
      "options": {
        "colorMode": "background",
        "graphMode": "none",
        "justifyMode": "center",
        "orientation": "auto",
        "reduceOptions": {
          "calcs": [
            "lastNotNull"
          ],
          "fields": "",
          "values": false
        },
        "textMode": "auto"
      },
      "fieldConfig": {
        "defaults": {
          "unit": "%",
          "thresholds": {
            "mode": "absolute",
            "steps": [
              {
                "color": "green",
                "value": null
              }
            ]
          },
          "mappings": [],
          "color": {
            "mode": "thresholds"
          }
        },
        "overrides": []
      },
      "targets": [
        {
          "datasource": {
            "type": "influxdb",
            "uid": "cfecbpgdhs5j4b"
          },
          "query": "from(bucket: \"bartos-homeassistant\")\n  |> range(start: -5m)\n  |> filter(fn: (r) => r._measurement == \"%\" and r._field == \"value\" and r.entity_id == \"lansing_st_weather_humidity\")\n  |> last()",
          "refId": "A"
        }
      ]
    },
    {
      "type": "timeseries",
      "title": "💧 Indoor vs Outdoor Humidity",
      "id": 19,
      "gridPos": {
        "h": 4,
        "w": 4,
        "x": 20,
        "y": 21
      },
      "datasource": {
        "type": "influxdb",
        "uid": "cfecbpgdhs5j4b"
      },
      "options": {
        "legend": {
          "displayMode": "list",
          "placement": "bottom",
          "showLegend": true
        },
        "tooltip": {
          "mode": "multi",
          "sort": "none"
        }
      },
      "fieldConfig": {
        "defaults": {
          "unit": "%",
          "color": {
            "mode": "palette-classic"
          }
        },
        "overrides": []
      },
      "targets": [
        {
          "datasource": {
            "type": "influxdb",
            "uid": "cfecbpgdhs5j4b"
          },
          "query": "from(bucket: \"bartos-homeassistant\")\n  |> range(start: v.timeRangeStart, stop: v.timeRangeStop)\n  |> filter(fn: (r) => r._measurement == \"%\" and r._field == \"value\" and (r.entity_id == \"average_house_humidity\" or r.entity_id == \"bathroom_zigbee_temperature_humidity\" or r.entity_id == \"bedroom_zigbee_tempurature_humidity\" or r.entity_id == \"lansing_st_weather_humidity\"))\n  |> map(fn: (r) => ({r with _field: r.entity_id}))",
          "refId": "A"
        }
      ]
    },
    {
      "type": "row",
      "title": "🌡 Thermostat Status",
      "id": 20,
      "collapsed": false,
      "gridPos": {
        "h": 1,
        "w": 24,
        "x": 0,
        "y": 25
      },
      "panels": []
    },
    {
      "type": "stat",
      "title": "Current Temp",
      "id": 21,
      "gridPos": {
        "h": 4,
        "w": 4,
        "x": 0,
        "y": 26
      },
      "datasource": {
        "type": "influxdb",
        "uid": "cfecbpgdhs5j4b"
      },
      "options": {
        "colorMode": "background",
        "graphMode": "none",
        "justifyMode": "center",
        "orientation": "auto",
        "reduceOptions": {
          "calcs": [
            "lastNotNull"
          ],
          "fields": "",
          "values": false
        },
        "textMode": "auto"
      },
      "fieldConfig": {
        "defaults": {
          "unit": "°F",
          "thresholds": {
            "mode": "absolute",
            "steps": [
              {
                "color": "blue",
                "value": null
              },
              {
                "color": "green",
                "value": 65
              },
              {
                "color": "yellow",
                "value": 78
              },
              {
                "color": "red",
                "value": 85
              }
            ]
          },
          "mappings": [],
          "color": {
            "mode": "thresholds"
          }
        },
        "overrides": []
      },
      "targets": [
        {
          "datasource": {
            "type": "influxdb",
            "uid": "cfecbpgdhs5j4b"
          },
          "query": "from(bucket: \"bartos-homeassistant\")\n  |> range(start: -5m)\n  |> filter(fn: (r) => r._measurement == \"°F\" and r._field == \"value\" and r.entity_id == \"smart_thermostat_effective_temperature_fahrenheit\")\n  |> last()",
          "refId": "A"
        }
      ]
    },
    {
      "type": "stat",
      "title": "Main Floor Temp",
      "id": 22,
      "gridPos": {
        "h": 4,
        "w": 4,
        "x": 4,
        "y": 26
      },
      "datasource": {
        "type": "influxdb",
        "uid": "cfecbpgdhs5j4b"
      },
      "options": {
        "colorMode": "background",
        "graphMode": "none",
        "justifyMode": "center",
        "orientation": "auto",
        "reduceOptions": {
          "calcs": [
            "lastNotNull"
          ],
          "fields": "",
          "values": false
        },
        "textMode": "auto"
      },
      "fieldConfig": {
        "defaults": {
          "unit": "°F",
          "thresholds": {
            "mode": "absolute",
            "steps": [
              {
                "color": "blue",
                "value": null
              },
              {
                "color": "green",
                "value": 65
              },
              {
                "color": "yellow",
                "value": 78
              },
              {
                "color": "red",
                "value": 85
              }
            ]
          },
          "mappings": [],
          "color": {
            "mode": "thresholds"
          }
        },
        "overrides": []
      },
      "targets": [
        {
          "datasource": {
            "type": "influxdb",
            "uid": "cfecbpgdhs5j4b"
          },
          "query": "from(bucket: \"bartos-homeassistant\")\n  |> range(start: -5m)\n  |> filter(fn: (r) => r._measurement == \"°F\" and r._field == \"value\" and r.entity_id == \"main_floor_temperature\")\n  |> last()",
          "refId": "A"
        }
      ]
    },
    {
      "type": "stat",
      "title": "HVAC Action",
      "id": 23,
      "gridPos": {
        "h": 4,
        "w": 4,
        "x": 8,
        "y": 26
      },
      "datasource": {
        "type": "influxdb",
        "uid": "cfecbpgdhs5j4b"
      },
      "options": {
        "colorMode": "background",
        "graphMode": "none",
        "justifyMode": "center",
        "orientation": "auto",
        "reduceOptions": {
          "calcs": [
            "lastNotNull"
          ],
          "fields": "",
          "values": false
        },
        "textMode": "auto"
      },
      "fieldConfig": {
        "defaults": {
          "unit": "string",
          "thresholds": {
            "mode": "absolute",
            "steps": [
              {
                "color": "green",
                "value": null
              }
            ]
          },
          "mappings": [],
          "color": {
            "mode": "thresholds"
          }
        },
        "overrides": []
      },
      "targets": [
        {
          "datasource": {
            "type": "influxdb",
            "uid": "cfecbpgdhs5j4b"
          },
          "query": "from(bucket: \"bartos-homeassistant\")\n  |> range(start: -5m)\n  |> filter(fn: (r) => r.domain == \"climate\" and r._field == \"hvac_action_str\" and r.entity_id == \"smart_thermostat\")\n  |> last()",
          "refId": "A"
        }
      ]
    },
    {
      "type": "stat",
      "title": "🔥 Heating Cycles Today",
      "id": 24,
      "gridPos": {
        "h": 4,
        "w": 4,
        "x": 12,
        "y": 26
      },
      "datasource": {
        "type": "influxdb",
        "uid": "cfecbpgdhs5j4b"
      },
      "options": {
        "colorMode": "background",
        "graphMode": "none",
        "justifyMode": "center",
        "orientation": "auto",
        "reduceOptions": {
          "calcs": [
            "lastNotNull"
          ],
          "fields": "",
          "values": false
        },
        "textMode": "auto"
      },
      "fieldConfig": {
        "defaults": {
          "unit": "short",
          "thresholds": {
            "mode": "absolute",
            "steps": [
              {
                "color": "green",
                "value": null
              }
            ]
          },
          "mappings": [],
          "color": {
            "mode": "thresholds"
          }
        },
        "overrides": []
      },
      "targets": [
        {
          "datasource": {
            "type": "influxdb",
            "uid": "cfecbpgdhs5j4b"
          },
          "query": "from(bucket: \"bartos-homeassistant\")\n  |> range(start: -5m)\n  |> filter(fn: (r) => r.domain == \"counter\" and r._field == \"value\" and r.entity_id == \"thermostat_heating_cycles_today\")\n  |> last()",
          "refId": "A"
        }
      ]
    },
    {
      "type": "stat",
      "title": "⚡ Heating Active",
      "id": 25,
      "gridPos": {
        "h": 4,
        "w": 4,
        "x": 16,
        "y": 26
      },
      "datasource": {
        "type": "influxdb",
        "uid": "cfecbpgdhs5j4b"
      },
      "options": {
        "colorMode": "background",
        "graphMode": "none",
        "justifyMode": "center",
        "orientation": "auto",
        "reduceOptions": {
          "calcs": [
            "lastNotNull"
          ],
          "fields": "",
          "values": false
        },
        "textMode": "auto"
      },
      "fieldConfig": {
        "defaults": {
          "unit": "",
          "thresholds": {
            "mode": "absolute",
            "steps": [
              {
                "color": "green",
                "value": null
              }
            ]
          },
          "mappings": [
            {
              "type": "value",
              "options": {
                "0": {
                  "text": "✅ Clear",
                  "color": "green",
                  "index": 0
                },
                "1": {
                  "text": "🚨 ALERT",
                  "color": "red",
                  "index": 1
                }
              }
            }
          ],
          "color": {
            "mode": "thresholds"
          }
        },
        "overrides": []
      },
      "targets": [
        {
          "datasource": {
            "type": "influxdb",
            "uid": "cfecbpgdhs5j4b"
          },
          "query": "from(bucket: \"bartos-homeassistant\")\n  |> range(start: -5m)\n  |> filter(fn: (r) => r.domain == \"binary_sensor\" and r._field == \"value\" and r.entity_id == \"smart_thermostat_heating_active\")\n  |> last()",
          "refId": "A"
        }
      ]
    },
    {
      "type": "stat",
      "title": "🔥 Stage 2 Active",
      "id": 26,
      "gridPos": {
        "h": 4,
        "w": 4,
        "x": 20,
        "y": 26
      },
      "datasource": {
        "type": "influxdb",
        "uid": "cfecbpgdhs5j4b"
      },
      "options": {
        "colorMode": "background",
        "graphMode": "none",
        "justifyMode": "center",
        "orientation": "auto",
        "reduceOptions": {
          "calcs": [
            "lastNotNull"
          ],
          "fields": "",
          "values": false
        },
        "textMode": "auto"
      },
      "fieldConfig": {
        "defaults": {
          "unit": "",
          "thresholds": {
            "mode": "absolute",
            "steps": [
              {
                "color": "green",
                "value": null
              }
            ]
          },
          "mappings": [
            {
              "type": "value",
              "options": {
                "0": {
                  "text": "✅ Clear",
                  "color": "green",
                  "index": 0
                },
                "1": {
                  "text": "🚨 ALERT",
                  "color": "red",
                  "index": 1
                }
              }
            }
          ],
          "color": {
            "mode": "thresholds"
          }
        },
        "overrides": []
      },
      "targets": [
        {
          "datasource": {
            "type": "influxdb",
            "uid": "cfecbpgdhs5j4b"
          },
          "query": "from(bucket: \"bartos-homeassistant\")\n  |> range(start: -5m)\n  |> filter(fn: (r) => r.domain == \"binary_sensor\" and r._field == \"value\" and r.entity_id == \"smart_thermostat_stage_2_active\")\n  |> last()",
          "refId": "A"
        }
      ]
    },
    {
      "type": "row",
      "title": "📈 HVAC History",
      "id": 27,
      "collapsed": false,
      "gridPos": {
        "h": 1,
        "w": 24,
        "x": 0,
        "y": 30
      },
      "panels": []
    },
    {
      "type": "timeseries",
      "title": "🔥 HVAC Active States (1=ON)",
      "id": 28,
      "gridPos": {
        "h": 8,
        "w": 12,
        "x": 0,
        "y": 31
      },
      "datasource": {
        "type": "influxdb",
        "uid": "cfecbpgdhs5j4b"
      },
      "options": {
        "legend": {
          "displayMode": "list",
          "placement": "bottom",
          "showLegend": true
        },
        "tooltip": {
          "mode": "multi",
          "sort": "none"
        }
      },
      "fieldConfig": {
        "defaults": {
          "unit": "short",
          "color": {
            "mode": "palette-classic"
          }
        },
        "overrides": []
      },
      "targets": [
        {
          "datasource": {
            "type": "influxdb",
            "uid": "cfecbpgdhs5j4b"
          },
          "query": "from(bucket: \"bartos-homeassistant\")\n  |> range(start: v.timeRangeStart, stop: v.timeRangeStop)\n  |> filter(fn: (r) => r.domain == \"binary_sensor\" and r._field == \"value\"\n      and (r.entity_id == \"smart_thermostat_heating_active\"\n        or r.entity_id == \"smart_thermostat_stage_2_active\"\n        or r.entity_id == \"smart_thermostat_fan_active\"))\n  |> map(fn: (r) => ({r with _field: r.entity_id}))",
          "refId": "A"
        }
      ]
    },
    {
      "type": "timeseries",
      "title": "🌡 Thermostat Temperature vs Time",
      "id": 29,
      "gridPos": {
        "h": 8,
        "w": 12,
        "x": 12,
        "y": 31
      },
      "datasource": {
        "type": "influxdb",
        "uid": "cfecbpgdhs5j4b"
      },
      "options": {
        "legend": {
          "displayMode": "list",
          "placement": "bottom",
          "showLegend": true
        },
        "tooltip": {
          "mode": "multi",
          "sort": "none"
        }
      },
      "fieldConfig": {
        "defaults": {
          "unit": "°F",
          "color": {
            "mode": "palette-classic"
          }
        },
        "overrides": []
      },
      "targets": [
        {
          "datasource": {
            "type": "influxdb",
            "uid": "cfecbpgdhs5j4b"
          },
          "query": "from(bucket: \"bartos-homeassistant\")\n  |> range(start: v.timeRangeStart, stop: v.timeRangeStop)\n  |> filter(fn: (r) => r._measurement == \"°F\" and r._field == \"value\" and (r.entity_id == \"smart_thermostat_effective_temperature_fahrenheit\" or r.entity_id == \"smart_thermostat_ecobee_temperature\" or r.entity_id == \"lansing_st_weather_temp\"))\n  |> map(fn: (r) => ({r with _field: r.entity_id}))",
          "refId": "A"
        }
      ]
    }
  ],
  "refresh": "1m",
  "schemaVersion": 38,
  "tags": [
    "home-assistant",
    "climate"
  ],
  "templating": {
    "list": []
  },
  "time": {
    "from": "now-24h",
    "to": "now"
  },
  "timepicker": {},
  "timezone": "America/Chicago",
  "title": "🌡 Climate & HVAC",
  "uid": "ha-climate-hvac",
  "version": 1
}